sphinx_theme_mochi/.gitignore
sphinx_theme_mochi/__init__.py
sphinx_theme_mochi/base.html
sphinx_theme_mochi/genindex.html
sphinx_theme_mochi/page.html
sphinx_theme_mochi/search.html
sphinx_theme_mochi/theme.conf
sphinx_theme_mochi/partials/brand.html
sphinx_theme_mochi/partials/footer.html
sphinx_theme_mochi/partials/icons.html
sphinx_theme_mochi/partials/mobile-header.html
sphinx_theme_mochi/partials/related-pages.html
sphinx_theme_mochi/partials/search.html
sphinx_theme_mochi/static/.gitignore
sphinx_theme_mochi/static/styles/theme.css
sphinx_theme_mochi-0.1.4.dist-info/entry_points.txt
sphinx_theme_mochi-0.1.4.dist-info/LICENSE
sphinx_theme_mochi-0.1.4.dist-info/WHEEL
sphinx_theme_mochi-0.1.4.dist-info/METADATA
sphinx_theme_mochi-0.1.4.dist-info/RECORD
